tldraw/__init__.py
tldraw/prompt.py
tldraw/static/bidirectional_stroke.css
tldraw/static/bidirectional_stroke.js
tldraw/static/coordinates.css
tldraw/static/coordinates.js
tldraw/static/debug.css
tldraw/static/debug.js
tldraw/static/debugging_shape.css
tldraw/static/debugging_shape.js
tldraw/static/flower_plot.css
tldraw/static/flower_plot.js
tldraw/static/get_stroke.css
tldraw/static/get_stroke.js
tldraw/static/image.css
tldraw/static/image.js
tldraw/static/image_and_array.css
tldraw/static/image_and_array.js
tldraw/static/image_set.css
tldraw/static/image_set.js
tldraw/static/makereal.css
tldraw/static/makereal.js
tldraw/static/makestatic_png.css
tldraw/static/makestatic_png.js
tldraw/static/makestatic_svg.css
tldraw/static/makestatic_svg.js
tldraw/static/makestatic_tldraw.css
tldraw/static/makestatic_tldraw.js
tldraw/static/makestatic_to_markdown.css
tldraw/static/makestatic_to_markdown.js
tldraw/static/minimal.css
tldraw/static/minimal.js
tldraw/static/reactive_color_picker.css
tldraw/static/reactive_color_picker.js
tldraw-3.0.0.dist-info/METADATA
tldraw-3.0.0.dist-info/WHEEL
tldraw-3.0.0.dist-info/licenses/LICENSE
tldraw-3.0.0.dist-info/RECORD
