Metadata-Version: 2.3
Name: tldraw
Version: 3.0.0
Summary: Tldraw for Jupyter
License-Expression: MIT
License-File: LICENSE
Requires-Dist: anywidget
Requires-Dist: ipykernel
Requires-Dist: ipylab
Requires-Dist: requests
Provides-Extra: dev
Requires-Dist: jupyterlab; extra == 'dev'
Requires-Dist: watchfiles; extra == 'dev'
